sra_wrapper/__init__.py
sra_wrapper/client.py
sra_wrapper/errors.py
sra_wrapper/responses.py
sra_wrapper-1.2.dist-info/WHEEL
sra_wrapper-1.2.dist-info/METADATA
sra_wrapper-1.2.dist-info/RECORD
